[{"model": "admin.logentry", "pk": 1, "fields": {"action_time": "2023-11-17T13:02:10.848Z", "user": 1, "content_type": 5, "object_id": "1", "object_repr": "admin", "action_flag": 2, "change_message": "[{\"changed\": {\"fields\": [\"\\u0412\\u042b\\u0431\\u043e\\u0440 \\u043f\\u043e\\u043b\\u0430 \", \"\\u0424\\u043e\\u0442\\u043e \\u043f\\u043e\\u043b\\u044c\\u0437\\u043e\\u0432\\u0430\\u0442\\u0435\\u043b\\u044f\"]}}]"}}, {"model": "admin.logentry", "pk": 2, "fields": {"action_time": "2023-11-21T10:48:53.994Z", "user": 1, "content_type": 5, "object_id": "2", "object_repr": "SuperAdm", "action_flag": 2, "change_message": "[{\"changed\": {\"fields\": [\"First name\", \"\\u0418\\u043c\\u044f \\u043f\\u043e\\u043b\\u044c\\u0437\\u043e\\u0432\\u0430\\u0442\\u0435\\u043b\\u044f\", \"\\u042d\\u043b\\u0435\\u043a\\u0442\\u0440\\u043e\\u043d\\u043d\\u0430\\u044f \\u043f\\u043e\\u0447\\u0442\\u0430\"]}}]"}}, {"model": "admin.logentry", "pk": 3, "fields": {"action_time": "2023-11-21T10:50:17.508Z", "user": 1, "content_type": 5, "object_id": "2", "object_repr": "SuperAdm", "action_flag": 2, "change_message": "[{\"changed\": {\"fields\": [\"\\u0424\\u043e\\u0442\\u043e \\u043f\\u043e\\u043b\\u044c\\u0437\\u043e\\u0432\\u0430\\u0442\\u0435\\u043b\\u044f\"]}}]"}}, {"model": "admin.logentry", "pk": 4, "fields": {"action_time": "2023-11-24T11:10:46.454Z", "user": 1, "content_type": 9, "object_id": "1", "object_repr": "Singer object (1)", "action_flag": 1, "change_message": "[{\"added\": {}}]"}}, {"model": "admin.logentry", "pk": 5, "fields": {"action_time": "2023-11-24T11:19:41.919Z", "user": 1, "content_type": 8, "object_id": "1", "object_repr": "Group object (1)", "action_flag": 1, "change_message": "[{\"added\": {}}]"}}, {"model": "admin.logentry", "pk": 6, "fields": {"action_time": "2023-11-24T11:39:29.549Z", "user": 1, "content_type": 7, "object_id": "1", "object_repr": "Рок", "action_flag": 1, "change_message": "[{\"added\": {}}]"}}, {"model": "admin.logentry", "pk": 7, "fields": {"action_time": "2023-11-24T11:39:35.986Z", "user": 1, "content_type": 7, "object_id": "2", "object_repr": "Поп", "action_flag": 1, "change_message": "[{\"added\": {}}]"}}, {"model": "admin.logentry", "pk": 8, "fields": {"action_time": "2023-11-24T11:39:53.241Z", "user": 1, "content_type": 7, "object_id": "3", "object_repr": "реп", "action_flag": 1, "change_message": "[{\"added\": {}}]"}}, {"model": "admin.logentry", "pk": 9, "fields": {"action_time": "2023-11-24T11:40:06.310Z", "user": 1, "content_type": 7, "object_id": "4", "object_repr": "Джаз", "action_flag": 1, "change_message": "[{\"added\": {}}]"}}, {"model": "admin.logentry", "pk": 10, "fields": {"action_time": "2023-11-24T11:40:42.378Z", "user": 1, "content_type": 7, "object_id": "3", "object_repr": "Реп", "action_flag": 2, "change_message": "[{\"changed\": {\"fields\": [\"\\u0416\\u0430\\u043d\\u0440\"]}}]"}}, {"model": "admin.logentry", "pk": 11, "fields": {"action_time": "2023-11-24T11:41:32.339Z", "user": 1, "content_type": 7, "object_id": "5", "object_repr": "Диско", "action_flag": 1, "change_message": "[{\"added\": {}}]"}}, {"model": "admin.logentry", "pk": 12, "fields": {"action_time": "2023-11-24T11:45:04.034Z", "user": 1, "content_type": 9, "object_id": "2", "object_repr": "Фредди Меркьюри", "action_flag": 1, "change_message": "[{\"added\": {}}]"}}, {"model": "admin.logentry", "pk": 13, "fields": {"action_time": "2023-11-24T11:49:22.675Z", "user": 1, "content_type": 9, "object_id": "3", "object_repr": "Giorgio Moroder", "action_flag": 1, "change_message": "[{\"added\": {}}]"}}, {"model": "admin.logentry", "pk": 14, "fields": {"action_time": "2023-11-24T11:52:56.645Z", "user": 1, "content_type": 9, "object_id": "5", "object_repr": "Snoop Dogg", "action_flag": 1, "change_message": "[{\"added\": {}}]"}}, {"model": "admin.logentry", "pk": 15, "fields": {"action_time": "2023-11-27T05:25:02.000Z", "user": 1, "content_type": 9, "object_id": "6", "object_repr": "Singer object (6)", "action_flag": 1, "change_message": "[{\"added\": {}}]"}}, {"model": "admin.logentry", "pk": 16, "fields": {"action_time": "2023-11-27T05:29:18.814Z", "user": 1, "content_type": 9, "object_id": "7", "object_repr": "Singer object (7)", "action_flag": 1, "change_message": "[{\"added\": {}}]"}}, {"model": "admin.logentry", "pk": 17, "fields": {"action_time": "2023-11-27T05:38:09.384Z", "user": 1, "content_type": 9, "object_id": "8", "object_repr": "Singer object (8)", "action_flag": 1, "change_message": "[{\"added\": {}}]"}}, {"model": "admin.logentry", "pk": 18, "fields": {"action_time": "2023-11-27T05:41:35.998Z", "user": 1, "content_type": 9, "object_id": "9", "object_repr": "Singer object (9)", "action_flag": 1, "change_message": "[{\"added\": {}}]"}}, {"model": "admin.logentry", "pk": 19, "fields": {"action_time": "2023-11-27T05:54:48.454Z", "user": 1, "content_type": 9, "object_id": "6", "object_repr": "JONY", "action_flag": 2, "change_message": "[{\"changed\": {\"fields\": [\"\\u041f\\u0441\\u0435\\u0432\\u0434\\u043e\\u043d\\u0438\\u043c\"]}}]"}}, {"model": "admin.logentry", "pk": 20, "fields": {"action_time": "2023-11-27T05:56:25.144Z", "user": 1, "content_type": 9, "object_id": "10", "object_repr": "Dan Reynolds", "action_flag": 1, "change_message": "[{\"added\": {}}]"}}, {"model": "admin.logentry", "pk": 21, "fields": {"action_time": "2023-11-27T06:25:22.867Z", "user": 1, "content_type": 9, "object_id": "11", "object_repr": "Луи Армстронг", "action_flag": 1, "change_message": "[{\"added\": {}}]"}}, {"model": "admin.logentry", "pk": 22, "fields": {"action_time": "2023-11-27T06:28:38.140Z", "user": 1, "content_type": 8, "object_id": "2", "object_repr": "Imagine Dragons", "action_flag": 1, "change_message": "[{\"added\": {}}]"}}, {"model": "admin.logentry", "pk": 23, "fields": {"action_time": "2023-11-27T06:32:36.105Z", "user": 1, "content_type": 8, "object_id": "3", "object_repr": "BTS", "action_flag": 1, "change_message": "[{\"added\": {}}]"}}, {"model": "admin.logentry", "pk": 24, "fields": {"action_time": "2023-11-27T06:45:08.871Z", "user": 1, "content_type": 8, "object_id": "4", "object_repr": "Queen", "action_flag": 1, "change_message": "[{\"added\": {}}]"}}, {"model": "admin.logentry", "pk": 25, "fields": {"action_time": "2023-11-27T07:04:11.707Z", "user": 1, "content_type": 10, "object_id": "1", "object_repr": "Группа крови", "action_flag": 1, "change_message": "[{\"added\": {}}]"}}, {"model": "admin.logentry", "pk": 26, "fields": {"action_time": "2023-11-27T07:08:49.216Z", "user": 1, "content_type": 10, "object_id": "2", "object_repr": "Wiggle Wiggle", "action_flag": 1, "change_message": "[{\"added\": {}}]"}}, {"model": "admin.logentry", "pk": 27, "fields": {"action_time": "2023-11-29T12:25:20.100Z", "user": 1, "content_type": 10, "object_id": "3", "object_repr": "Звезда по имени солнце", "action_flag": 1, "change_message": "[{\"added\": {}}]"}}, {"model": "admin.logentry", "pk": 28, "fields": {"action_time": "2023-11-29T18:57:28.438Z", "user": 1, "content_type": 14, "object_id": "1", "object_repr": "Photo object (1)", "action_flag": 1, "change_message": "[{\"added\": {}}]"}}, {"model": "admin.logentry", "pk": 29, "fields": {"action_time": "2023-11-29T19:00:37.750Z", "user": 1, "content_type": 14, "object_id": "2", "object_repr": "Photo object (2)", "action_flag": 1, "change_message": "[{\"added\": {}}]"}}, {"model": "admin.logentry", "pk": 30, "fields": {"action_time": "2023-11-29T19:08:04.525Z", "user": 1, "content_type": 14, "object_id": "2", "object_repr": "Photo object (2)", "action_flag": 3, "change_message": ""}}, {"model": "admin.logentry", "pk": 31, "fields": {"action_time": "2023-11-29T19:08:04.528Z", "user": 1, "content_type": 14, "object_id": "1", "object_repr": "Photo object (1)", "action_flag": 3, "change_message": ""}}, {"model": "admin.logentry", "pk": 32, "fields": {"action_time": "2023-11-29T19:08:17.311Z", "user": 1, "content_type": 14, "object_id": "3", "object_repr": "Photo object (3)", "action_flag": 1, "change_message": "[{\"added\": {}}]"}}, {"model": "admin.logentry", "pk": 33, "fields": {"action_time": "2023-11-29T19:08:27.560Z", "user": 1, "content_type": 14, "object_id": "4", "object_repr": "Photo object (4)", "action_flag": 1, "change_message": "[{\"added\": {}}]"}}, {"model": "admin.logentry", "pk": 34, "fields": {"action_time": "2023-11-29T19:16:12.693Z", "user": 1, "content_type": 13, "object_id": "1", "object_repr": "Гуф пришел к вилле бывшей жены Юлии с кастетом", "action_flag": 1, "change_message": "[{\"added\": {}}]"}}, {"model": "admin.logentry", "pk": 35, "fields": {"action_time": "2023-11-29T19:59:44.162Z", "user": 1, "content_type": 14, "object_id": "5", "object_repr": "Новые российские альбомы: Big Baby Tape, Гио Пика и Кравц", "action_flag": 1, "change_message": "[{\"added\": {}}]"}}, {"model": "admin.logentry", "pk": 36, "fields": {"action_time": "2023-11-29T20:00:20.101Z", "user": 1, "content_type": 13, "object_id": "2", "object_repr": "Новые российские альбомы: Big Baby Tape, Гио Пика и Кравц", "action_flag": 1, "change_message": "[{\"added\": {}}]"}}, {"model": "admin.logentry", "pk": 37, "fields": {"action_time": "2023-11-30T05:52:33.851Z", "user": 1, "content_type": 14, "object_id": "6", "object_repr": "Default Title1", "action_flag": 1, "change_message": "[{\"added\": {}}]"}}, {"model": "admin.logentry", "pk": 38, "fields": {"action_time": "2023-11-30T05:52:54.797Z", "user": 1, "content_type": 13, "object_id": "1", "object_repr": "Гуф пришел к вилле бывшей жены Юлии с кастетом", "action_flag": 2, "change_message": "[{\"changed\": {\"fields\": [\"Photos\"]}}]"}}, {"model": "admin.logentry", "pk": 39, "fields": {"action_time": "2023-11-30T05:53:25.795Z", "user": 1, "content_type": 13, "object_id": "1", "object_repr": "Гуф пришел к вилле бывшей жены Юлии с кастетом", "action_flag": 2, "change_message": "[{\"changed\": {\"fields\": [\"Photos\"]}}]"}}, {"model": "admin.logentry", "pk": 40, "fields": {"action_time": "2023-11-30T05:53:45.388Z", "user": 1, "content_type": 13, "object_id": "2", "object_repr": "Новые российские альбомы: Big Baby Tape, Гио Пика и Кравц", "action_flag": 2, "change_message": "[{\"changed\": {\"fields\": [\"Photos\"]}}]"}}, {"model": "admin.logentry", "pk": 41, "fields": {"action_time": "2023-11-30T05:58:35.305Z", "user": 1, "content_type": 14, "object_id": "7", "object_repr": "Настасья", "action_flag": 1, "change_message": "[{\"added\": {}}]"}}, {"model": "admin.logentry", "pk": 42, "fields": {"action_time": "2023-11-30T05:58:54.565Z", "user": 1, "content_type": 14, "object_id": "8", "object_repr": "настасья", "action_flag": 1, "change_message": "[{\"added\": {}}]"}}, {"model": "admin.logentry", "pk": 43, "fields": {"action_time": "2023-11-30T05:59:39.812Z", "user": 1, "content_type": 13, "object_id": "3", "object_repr": "Настасья Самбурская раскрыла свою самую необычную роль", "action_flag": 1, "change_message": "[{\"added\": {}}]"}}, {"model": "admin.logentry", "pk": 44, "fields": {"action_time": "2023-11-30T06:05:44.934Z", "user": 1, "content_type": 14, "object_id": "9", "object_repr": "Инстасамка", "action_flag": 1, "change_message": "[{\"added\": {}}]"}}, {"model": "admin.logentry", "pk": 45, "fields": {"action_time": "2023-11-30T06:06:30.841Z", "user": 1, "content_type": 13, "object_id": "4", "object_repr": "Инстасамка пожаловалась на слив фото с ее тайной свадьбы", "action_flag": 1, "change_message": "[{\"added\": {}}]"}}, {"model": "admin.logentry", "pk": 46, "fields": {"action_time": "2023-11-30T06:36:06.995Z", "user": 1, "content_type": 13, "object_id": "3", "object_repr": "Настасья Самбурская раскрыла свою самую необычную роль", "action_flag": 2, "change_message": "[{\"changed\": {\"fields\": [\"Photos\"]}}]"}}, {"model": "admin.logentry", "pk": 47, "fields": {"action_time": "2023-11-30T06:36:15.249Z", "user": 1, "content_type": 13, "object_id": "2", "object_repr": "Новые российские альбомы: Big Baby Tape, Гио Пика и Кравц", "action_flag": 2, "change_message": "[{\"changed\": {\"fields\": [\"Photos\"]}}]"}}, {"model": "admin.logentry", "pk": 48, "fields": {"action_time": "2023-11-30T06:36:22.931Z", "user": 1, "content_type": 13, "object_id": "1", "object_repr": "Гуф пришел к вилле бывшей жены Юлии с кастетом", "action_flag": 2, "change_message": "[{\"changed\": {\"fields\": [\"Photos\"]}}]"}}, {"model": "admin.logentry", "pk": 49, "fields": {"action_time": "2023-11-30T09:25:23.590Z", "user": 1, "content_type": 13, "object_id": "4", "object_repr": "Инстасамка пожаловалась на слив фото с ее тайной свадьбы", "action_flag": 2, "change_message": "[{\"changed\": {\"fields\": [\"Photos\"]}}]"}}, {"model": "admin.logentry", "pk": 50, "fields": {"action_time": "2023-11-30T09:28:26.966Z", "user": 1, "content_type": 13, "object_id": "4", "object_repr": "Инстасамка пожаловалась на слив фото с ее тайной свадьбы", "action_flag": 2, "change_message": "[{\"changed\": {\"fields\": [\"Photos\"]}}]"}}, {"model": "admin.logentry", "pk": 51, "fields": {"action_time": "2023-11-30T09:33:55.525Z", "user": 1, "content_type": 13, "object_id": "3", "object_repr": "Настасья Самбурская раскрыла свою самую необычную роль", "action_flag": 2, "change_message": "[{\"changed\": {\"fields\": [\"Photos\"]}}]"}}, {"model": "admin.logentry", "pk": 52, "fields": {"action_time": "2023-11-30T09:34:26.025Z", "user": 1, "content_type": 13, "object_id": "3", "object_repr": "Настасья Самбурская раскрыла свою самую необычную роль", "action_flag": 2, "change_message": "[{\"changed\": {\"fields\": [\"Photos\"]}}]"}}, {"model": "admin.logentry", "pk": 53, "fields": {"action_time": "2023-11-30T09:34:37.947Z", "user": 1, "content_type": 13, "object_id": "4", "object_repr": "Инстасамка пожаловалась на слив фото с ее тайной свадьбы", "action_flag": 2, "change_message": "[{\"changed\": {\"fields\": [\"Photos\"]}}]"}}, {"model": "admin.logentry", "pk": 54, "fields": {"action_time": "2023-11-30T09:34:52.351Z", "user": 1, "content_type": 13, "object_id": "2", "object_repr": "Новые российские альбомы: Big Baby Tape, Гио Пика и Кравц", "action_flag": 2, "change_message": "[]"}}, {"model": "admin.logentry", "pk": 55, "fields": {"action_time": "2023-11-30T09:35:02.530Z", "user": 1, "content_type": 13, "object_id": "1", "object_repr": "Гуф пришел к вилле бывшей жены Юлии с кастетом", "action_flag": 2, "change_message": "[{\"changed\": {\"fields\": [\"Photos\"]}}]"}}, {"model": "auth.permission", "pk": 1, "fields": {"name": "Can add permission", "content_type": 1, "codename": "add_permission"}}, {"model": "auth.permission", "pk": 2, "fields": {"name": "Can change permission", "content_type": 1, "codename": "change_permission"}}, {"model": "auth.permission", "pk": 3, "fields": {"name": "Can delete permission", "content_type": 1, "codename": "delete_permission"}}, {"model": "auth.permission", "pk": 4, "fields": {"name": "Can view permission", "content_type": 1, "codename": "view_permission"}}, {"model": "auth.permission", "pk": 5, "fields": {"name": "Can add group", "content_type": 2, "codename": "add_group"}}, {"model": "auth.permission", "pk": 6, "fields": {"name": "Can change group", "content_type": 2, "codename": "change_group"}}, {"model": "auth.permission", "pk": 7, "fields": {"name": "Can delete group", "content_type": 2, "codename": "delete_group"}}, {"model": "auth.permission", "pk": 8, "fields": {"name": "Can view group", "content_type": 2, "codename": "view_group"}}, {"model": "auth.permission", "pk": 9, "fields": {"name": "Can add content type", "content_type": 3, "codename": "add_contenttype"}}, {"model": "auth.permission", "pk": 10, "fields": {"name": "Can change content type", "content_type": 3, "codename": "change_contenttype"}}, {"model": "auth.permission", "pk": 11, "fields": {"name": "Can delete content type", "content_type": 3, "codename": "delete_contenttype"}}, {"model": "auth.permission", "pk": 12, "fields": {"name": "Can view content type", "content_type": 3, "codename": "view_contenttype"}}, {"model": "auth.permission", "pk": 13, "fields": {"name": "Can add session", "content_type": 4, "codename": "add_session"}}, {"model": "auth.permission", "pk": 14, "fields": {"name": "Can change session", "content_type": 4, "codename": "change_session"}}, {"model": "auth.permission", "pk": 15, "fields": {"name": "Can delete session", "content_type": 4, "codename": "delete_session"}}, {"model": "auth.permission", "pk": 16, "fields": {"name": "Can view session", "content_type": 4, "codename": "view_session"}}, {"model": "auth.permission", "pk": 17, "fields": {"name": "Can add user", "content_type": 5, "codename": "add_user"}}, {"model": "auth.permission", "pk": 18, "fields": {"name": "Can change user", "content_type": 5, "codename": "change_user"}}, {"model": "auth.permission", "pk": 19, "fields": {"name": "Can delete user", "content_type": 5, "codename": "delete_user"}}, {"model": "auth.permission", "pk": 20, "fields": {"name": "Can view user", "content_type": 5, "codename": "view_user"}}, {"model": "auth.permission", "pk": 21, "fields": {"name": "Can add log entry", "content_type": 6, "codename": "add_logentry"}}, {"model": "auth.permission", "pk": 22, "fields": {"name": "Can change log entry", "content_type": 6, "codename": "change_logentry"}}, {"model": "auth.permission", "pk": 23, "fields": {"name": "Can delete log entry", "content_type": 6, "codename": "delete_logentry"}}, {"model": "auth.permission", "pk": 24, "fields": {"name": "Can view log entry", "content_type": 6, "codename": "view_logentry"}}, {"model": "auth.permission", "pk": 25, "fields": {"name": "Can add Жанр", "content_type": 7, "codename": "add_genre"}}, {"model": "auth.permission", "pk": 26, "fields": {"name": "Can change Жанр", "content_type": 7, "codename": "change_genre"}}, {"model": "auth.permission", "pk": 27, "fields": {"name": "Can delete Жанр", "content_type": 7, "codename": "delete_genre"}}, {"model": "auth.permission", "pk": 28, "fields": {"name": "Can view Жанр", "content_type": 7, "codename": "view_genre"}}, {"model": "auth.permission", "pk": 29, "fields": {"name": "Can add group", "content_type": 8, "codename": "add_group"}}, {"model": "auth.permission", "pk": 30, "fields": {"name": "Can change group", "content_type": 8, "codename": "change_group"}}, {"model": "auth.permission", "pk": 31, "fields": {"name": "Can delete group", "content_type": 8, "codename": "delete_group"}}, {"model": "auth.permission", "pk": 32, "fields": {"name": "Can view group", "content_type": 8, "codename": "view_group"}}, {"model": "auth.permission", "pk": 33, "fields": {"name": "Can add singer", "content_type": 9, "codename": "add_singer"}}, {"model": "auth.permission", "pk": 34, "fields": {"name": "Can change singer", "content_type": 9, "codename": "change_singer"}}, {"model": "auth.permission", "pk": 35, "fields": {"name": "Can delete singer", "content_type": 9, "codename": "delete_singer"}}, {"model": "auth.permission", "pk": 36, "fields": {"name": "Can view singer", "content_type": 9, "codename": "view_singer"}}, {"model": "auth.permission", "pk": 37, "fields": {"name": "Can add Музыка", "content_type": 10, "codename": "add_music"}}, {"model": "auth.permission", "pk": 38, "fields": {"name": "Can change Музыка", "content_type": 10, "codename": "change_music"}}, {"model": "auth.permission", "pk": 39, "fields": {"name": "Can delete Музыка", "content_type": 10, "codename": "delete_music"}}, {"model": "auth.permission", "pk": 40, "fields": {"name": "Can view Музыка", "content_type": 10, "codename": "view_music"}}, {"model": "auth.permission", "pk": 41, "fields": {"name": "Can add photo", "content_type": 11, "codename": "add_photo"}}, {"model": "auth.permission", "pk": 42, "fields": {"name": "Can change photo", "content_type": 11, "codename": "change_photo"}}, {"model": "auth.permission", "pk": 43, "fields": {"name": "Can delete photo", "content_type": 11, "codename": "delete_photo"}}, {"model": "auth.permission", "pk": 44, "fields": {"name": "Can view photo", "content_type": 11, "codename": "view_photo"}}, {"model": "auth.permission", "pk": 45, "fields": {"name": "Can add news", "content_type": 12, "codename": "add_news"}}, {"model": "auth.permission", "pk": 46, "fields": {"name": "Can change news", "content_type": 12, "codename": "change_news"}}, {"model": "auth.permission", "pk": 47, "fields": {"name": "Can delete news", "content_type": 12, "codename": "delete_news"}}, {"model": "auth.permission", "pk": 48, "fields": {"name": "Can view news", "content_type": 12, "codename": "view_news"}}, {"model": "auth.permission", "pk": 49, "fields": {"name": "Can add Новость", "content_type": 13, "codename": "add_news"}}, {"model": "auth.permission", "pk": 50, "fields": {"name": "Can change Новость", "content_type": 13, "codename": "change_news"}}, {"model": "auth.permission", "pk": 51, "fields": {"name": "Can delete Новость", "content_type": 13, "codename": "delete_news"}}, {"model": "auth.permission", "pk": 52, "fields": {"name": "Can view Новость", "content_type": 13, "codename": "view_news"}}, {"model": "auth.permission", "pk": 53, "fields": {"name": "Can add photo", "content_type": 14, "codename": "add_photo"}}, {"model": "auth.permission", "pk": 54, "fields": {"name": "Can change photo", "content_type": 14, "codename": "change_photo"}}, {"model": "auth.permission", "pk": 55, "fields": {"name": "Can delete photo", "content_type": 14, "codename": "delete_photo"}}, {"model": "auth.permission", "pk": 56, "fields": {"name": "Can view photo", "content_type": 14, "codename": "view_photo"}}, {"model": "contenttypes.contenttype", "pk": 1, "fields": {"app_label": "auth", "model": "permission"}}, {"model": "contenttypes.contenttype", "pk": 2, "fields": {"app_label": "auth", "model": "group"}}, {"model": "contenttypes.contenttype", "pk": 3, "fields": {"app_label": "contenttypes", "model": "contenttype"}}, {"model": "contenttypes.contenttype", "pk": 4, "fields": {"app_label": "sessions", "model": "session"}}, {"model": "contenttypes.contenttype", "pk": 5, "fields": {"app_label": "accounts", "model": "user"}}, {"model": "contenttypes.contenttype", "pk": 6, "fields": {"app_label": "admin", "model": "logentry"}}, {"model": "contenttypes.contenttype", "pk": 7, "fields": {"app_label": "music", "model": "genre"}}, {"model": "contenttypes.contenttype", "pk": 8, "fields": {"app_label": "music", "model": "group"}}, {"model": "contenttypes.contenttype", "pk": 9, "fields": {"app_label": "music", "model": "singer"}}, {"model": "contenttypes.contenttype", "pk": 10, "fields": {"app_label": "music", "model": "music"}}, {"model": "contenttypes.contenttype", "pk": 11, "fields": {"app_label": "music", "model": "photo"}}, {"model": "contenttypes.contenttype", "pk": 12, "fields": {"app_label": "music", "model": "news"}}, {"model": "contenttypes.contenttype", "pk": 13, "fields": {"app_label": "news", "model": "news"}}, {"model": "contenttypes.contenttype", "pk": 14, "fields": {"app_label": "news", "model": "photo"}}, {"model": "sessions.session", "pk": "tjp4agxxoj759l1plgirwvgfsuz5hxk3", "fields": {"session_data": ".eJxVjDsOwjAQBe_iGln-bbKmpOcM1q4_OIAcKU4qxN0hUgpo38y8lwi0rTVsPS9hSuIstDj9bkzxkdsO0p3abZZxbusysdwVedAur3PKz8vh_h1U6vVbgwX0qmi2pBKOwBmBGLRhJEw2FjuwjQOhjc6AM8yFowKHyMl7N4r3B900N9Q:1r6U6y:aOXJkoF1U66gMEKFI-WdvTQR7znH8boF4WBXWwzl2WQ", "expire_date": "2023-12-08T11:12:40.826Z"}}, {"model": "accounts.user", "pk": 1, "fields": {"password": "pbkdf2_sha256$600000$cSTURGBcyaGX8Y3PIkDITj$Nb+RAGPGWVC9cEambrPNEQFpBvajttXFDUCtHaGVIBU=", "last_login": "2023-11-24T11:12:40.823Z", "is_superuser": true, "first_name": "", "last_name": "", "is_staff": true, "is_active": true, "date_joined": "2023-11-17T12:52:28Z", "username": "admin", "email": "admin@mail.ru", "sex": "male", "age": null, "phone": null, "created": "2023-11-17T12:52:28.935Z", "avatar": "media/images/Makise.Kurisu.full.513955.jpg", "groups": [], "user_permissions": [], "favorite_song": []}}, {"model": "accounts.user", "pk": 2, "fields": {"password": "pbkdf2_sha256$600000$JBicy4TV3BnfIV9ZTY6X9k$MdU3srmFB0KvppY+/YyfE4X4dLR1O8viwJh4gGbFmTw=", "last_login": "2023-11-24T11:11:08.138Z", "is_superuser": false, "first_name": "Sandora", "last_name": "", "is_staff": false, "is_active": true, "date_joined": "2023-11-21T10:46:02Z", "username": "SuperAdm", "email": "admin@gmail.com", "sex": "Мужчина", "age": null, "phone": null, "created": "2023-11-21T10:46:04.083Z", "avatar": "media/images/Makise.Kurisu.full.513955_CPkn0vT.jpg", "groups": [], "user_permissions": [], "favorite_song": []}}, {"model": "music.singer", "pk": 1, "fields": {"first_name": "Цой", "last_name": "Виктор", "nickname": null, "photo": "singers/1500820210_898152_original.jpg", "biography": "Дата рождения 21 июня 1962 (1962-06-21). Место рождения Ленинград, РСФСР, СССР. Дата смерти 15 августа 1990 (1990-08-15) (28 лет). Место смерти 35-й км шоссе «Слока — Талси», Тукумский район, Латвийская ССР, СССР. Похоронен Богословское кладбище Страна. Профессии поэт, поэт-песенник, певец, гитарист, композитор, актёр, художник, рок-музыкант, автор-исполнитель. Годы активности 1978 — 1990 Певческий голос баритон."}}, {"model": "music.singer", "pk": 2, "fields": {"first_name": "Фредди", "last_name": "Меркьюри", "nickname": null, "photo": "singers/043c5c0b1008b4060e75479e7f4fa912.jpg", "biography": "Фредди Меркьюри известен как автор многих композиций группы «Queen», солистом которой он был долгие годы. В 2008 году его назвали одним из величайших рок-исполнителей и обладателем уникального голоса за всю историю современной музыки.\r\nИсточник: https://biographe.ru/znamenitosti/freddi-merkuri"}}, {"model": "music.singer", "pk": 3, "fields": {"first_name": "Giorgio", "last_name": "Moroder", "nickname": null, "photo": "singers/2014GiorgioMoroder_Getty465242303140214.jpg", "biography": "Giorgio Moroder родился 26 апреля 1940 года в городе Ortisei, Италия. Более всего известен, как пионер электронной музыки, как один из первых открывателей дискомузыки семидесятых, а также как автор музыки к кинофильмам.\r\n\r\nGiorgio Moroder первоначально начинал свою карьеру как гитарист. В 19 лет он выступал в ночных клубах по всей Европе, исполняя кавер-версии знаменитых музыкантов."}}, {"model": "music.singer", "pk": 5, "fields": {"first_name": null, "last_name": null, "nickname": "Snoop Dogg", "photo": "singers/zagruzheno_M9BQuSE.jpg", "biography": "Настоящее имя музыканта – Келвин Бродус. Его родным городом является Лонг-Бич, здесь он родился в 71-м году. Звучный псевдоним исполнитель не придумал самостоятельно. Прозвище появилось благодаря любви Келвина к обаятельному псу из комиксов, которого так и звали – Снуп Дог. Мама частенько называла сына этим прозвищем, в итоге оно закрепилось за музыкантом. Спустя много лет прозвище превратилось в успешный музыкальный бренд.\r\n\r\nУ Келвина была два брата. Его отец – ветеран Вьетнама. Через несколько месяцев после рождения Келвина отец оставил семью и ушел из дома. Воспитанием мальчиков занимался преимущественно дедушка. В дальнейшем музыкант не раз признавался, что в детстве ему не хватало отцовского воспитания. Но негативный детский опыт является причиной того, что сам Снуп стал прекрасным отцом. Он старался не повторять ошибок своих родителей и в дальнейшем прославился как примерный семьянин.\r\nИсточник: https://biographe.ru/znamenitosti/snoop-dogg"}}, {"model": "music.singer", "pk": 6, "fields": {"first_name": null, "last_name": null, "nickname": "JONY", "photo": "singers/i.webp", "biography": "Талантливого музыкального исполнителя из Азербайджана Джахида Гусейнли поклонники знают под псевдонимом Jony. В начале своего творческого пути молодой человек пытался сделать карьеру в бизнесе, однако чувствовал себя несчастливым, так как занимался нелюбимым делом. Только в музыкальном мире у него появилась возможность показать свои настоящие таланты и молодой человек множество раз доказал тысячам слушателей, что он способен на многое. На сегодняшний день композициям исполнителя подпевают на улицах и в машинах, а на концерте непременно собираются тысячи слушателей.\r\n\r\nДжахид родился 29 февраля 1996 года в азербайджанском городе Баку. В семье будущий вокалист воспитывался вместе с братом. Наследники ни в чем себе не отказывали, так как отец имел собственный бизнес и полностью обеспечивал семью. Когда парню исполнилось всего четыре года, семья решила переехать в Москву.\r\nИсточник: https://biographe.ru/znamenitosti/jony"}}, {"model": "music.singer", "pk": 7, "fields": {"first_name": "Джон", "last_name": "Леннон", "nickname": null, "photo": "singers/1200x2778_original_art_2019_09_5d79f9e15c06b.jpeg", "biography": "Джон Леннон — известный рок-музыкант, поэт, композитор, певец, писатель, художник, общественный активист. Основал группу «Битлз» и был ее участником, самый популярный музыкант 20-го века.\r\n\r\nИмя Джона Леннона навечно занесено в список самых прославленных британцев XX века. Согласно рейтинга ВВС, он занимает восьмое место среди сотни британцев, оказавших влияние на ее историю. Леннон ратовал за мир и свободу, за равенство и братство, благодаря чему стал одним из ведущих общественных деятелей 60-70-х годов прошлого века и кумиром хиппи.\r\n\r\n\r\nИсточник: https://biographe.ru/znamenitosti/john-lennon"}}, {"model": "music.singer", "pk": 8, "fields": {"first_name": "Андре", "last_name": "Ромелл Янг", "nickname": "Dr.Dre", "photo": "singers/orig_1.jpeg", "biography": "Dr. Dre\r\nДоктор Дре (настоящее имя Андре Ромелл Янг) — американский рэпер и продюсер, один из наиболее успешных битмейкеров в рэп-музыке.\r\nСчитается важнейшей фигурой в популяризации стиля джи-фанк — одного из стилей хип-хопа Западного побережья.\r\nПомимо сольного творчества, Доктор Дре продюсировал альбомы многочисленных рэперов, среди которых были Snoop Dogg, Эминем, 50 Cent, Xzibit, 2Pac, The Game и Busta Rhymes."}}, {"model": "music.singer", "pk": 9, "fields": {"first_name": "Джонгук", "last_name": "Чон", "nickname": "JK", "photo": "singers/i_1.webp", "biography": "Чон Чонгук\r\nЧон Джонгук (Jungkook) — южнокорейский певец, автор песен и музыкальный продюсер.\r\nОн является самым младшим участником (макне) и главным вокалистом бой-бэнда BTS.\r\nСогласно данным Корейской ассоциации звукозаписывающих компаний (KOMCA), Джонгук является автором шести композиций в дискографии группы."}}, {"model": "music.singer", "pk": 10, "fields": {"first_name": "Dan", "last_name": "Reynolds", "nickname": null, "photo": "singers/221380_screenshots_20180814083938_2.jpg", "biography": "Дэн Рейнольдс\r\nДэн Рейнольдс (полное имя Daniel Coulter Reynolds) — американский певец, автор песен, музыкант, мультиинструменталист и музыкальный продюсер, актер. Вокалист и основатель рок-группы Imagine Dragons."}}, {"model": "music.singer", "pk": 11, "fields": {"first_name": "Луи", "last_name": "Армстронг", "nickname": null, "photo": "singers/imgpreview.jpeg", "biography": "Луи Армстронг\r\nЛуи Армстронг (при рождении Луи Дэниел Армстронг) — американский джазовый музыкант, трубач и вокалист.\r\nРодился 4 августа 1901 года в Новом Орлеане, штат Луизиана, США.\r\nВведён в Зал славы премии «Грэмми». Оказал одно из наибольших влияний на развитие джаза и внёс значительный вклад в его популяризацию во всём мире.\r\nПолучил многочисленные награды, в том числе премию «Грэмми» (1965), а также посмертную победу на премии «Grammy Lifetime Achievement Award» в 1972 году и введение в Национальный зал славы ритм-энд-блюза в 2017 году."}}, {"model": "music.group", "pk": 1, "fields": {"group_name": "Кино", "photo": "groups/8p0klNVHcYthedsWofrFSSBP-sdTzLt1so0-uZIeVIWoxsC2h-vsZmMEZU2BijeDekebFGYCXor2yFo7dIx9IaFs.jpg", "biography": "Биография группы «Кино» начинается со встречи участников ленинградских бит-коллективов «Палата № 6» и «Пилигрим». Виктор Цой был басистом в первом, а его будущие коллеги Алексей Рыбин и Олег Валинский — гитаристом и барабанщиком во втором. Летом 1981 года друзья поехали на отдых в Крым, где решили создать общую команду. Изначально группа «Кино» называлась «Гарин и гиперболоиды». К идее подтолкнул фантастический роман Алексея Толстого «Гиперболоид инженера Гарина».", "created_date": "1982-06-19", "singer": [1]}}, {"model": "music.group", "pk": 2, "fields": {"group_name": "Imagine Dragons", "photo": "groups/bf7d14eb08301fbfeb76447a924301a3.jpeg", "biography": "Imagine Dragons\r\nАмериканская поп-рок-группа, образованная в 2008 году в городе Лас-Вегас, США. Стали известны после выпуска дебютного студийного альбома Night Visions в сентябре 2012 года.", "created_date": "2008-11-27", "singer": [10]}}, {"model": "music.group", "pk": 3, "fields": {"group_name": "BTS", "photo": "groups/266606508_4664ee356ef56180e896f54ed5919714.jpg", "biography": "История создания BTS Как переводится BTS? BTS — это сокращение от «Bangtan Sonyeondan», что в переводе с корейского означает 'пуленепробиваемые бойскауты'. В Японии название бойз-бэнда звучит немного иначе — «Бодан Сенендан», — но переводится также. Также группа известна под названием Bangtan Boys или Beyond The Scene. Создание BTS началось в 2010 году. Именно тогда генеральному директору лейбла Big Hit Entertainment Пану Си Хёку пришла идея сформировать новый хип-хоп коллектив. Центральное место в нем отводилось RM, который был известным в музыкальном андеграунде Сеула рэпером. Читайте больше:", "created_date": "2010-11-27", "singer": [9]}}, {"model": "music.group", "pk": 4, "fields": {"group_name": "Queen", "photo": "groups/Queen_Purple_Final_750x750-2048x2048.jpg", "biography": "Queen\r\nБританская рок-группа, добившаяся широчайшей известности в середине 1970-х годов, и одна из наиболее успешных групп в истории рок-музыки.\r\nСредства массовой информации называют группу «культовой» и пишут, что она и по сей день имеет сотни миллионов поклонников. Группа выпустила пятнадцать студийных альбомов, пять концертных и многочисленные сборники. Восемнадцать хитов «Queen» занимали первые места в чартах разных стран. Каждый участник группы является автором как минимум одного хита, достигавшего вершины британского чарта. Концертные выступления группы также были признаны одними из самых ярких и значимых за всю историю рока.", "created_date": "1970-06-27", "singer": [2]}}, {"model": "music.genre", "pk": 1, "fields": {"name": "Рок", "slug": "rok"}}, {"model": "music.genre", "pk": 2, "fields": {"name": "Поп", "slug": "pop"}}, {"model": "music.genre", "pk": 3, "fields": {"name": "Реп", "slug": "rep"}}, {"model": "music.genre", "pk": 4, "fields": {"name": "Джаз", "slug": "dzhaz"}}, {"model": "music.genre", "pk": 5, "fields": {"name": "Диско", "slug": "disko"}}, {"model": "music.music", "pk": 1, "fields": {"title": "Группа крови", "group": 1, "public_date": "2023-11-27", "text_song": "Виктор Цой - Группа крови\r\n\r\nТеплое место, но улицы ждут отпечатков наших ног.\r\nЗвездная пыль - на сапогах.\r\nМягкое кресло, клетчатый плед, не нажатый вовремя курок.\r\nСолнечный день - в ослепительных снах.\r\n\r\nПрипев:\r\nГруппа крови - на рукаве, мой порядковый номер - на рукаве,\r\nПожелай мне удачи в бою, пожелай мне:\r\nНе остаться в этой траве, не остаться в этой траве.\r\nПожелай мне удачи, пожелай мне удачи!\r\n\r\nИ есть чем платить, но я не хочу победы любой ценой.\r\nЯ никому не хочу ставить ногу на грудь.\r\nЯ хотел бы остаться с тобой, просто остаться с тобой,\r\nНо высокая в небе звезда зовет меня в путь.\r\n\r\nПрипев:\r\nГруппа крови - на рукаве, мой порядковый номер - на рукаве,\r\nПожелай мне удачи в бою, пожелай мне:\r\nНе остаться в этой траве, не остаться в этой траве.\r\nПожелай мне удачи, пожелай мне удачи!", "music": "music/Kino_-_Gruppa_krovi_47829944.mp3", "singer": [1], "genre": [1]}}, {"model": "music.music", "pk": 2, "fields": {"title": "Wiggle Wiggle", "group": null, "public_date": "2017-11-27", "text_song": "Hey, yo, Jason\r\nSay somethin' to her\r\nHolla at her\r\n\r\nI got one question\r\nHow do you fit all that in them jeans?\r\n\r\nYou know what to do with that big fat butt\r\n\r\nWiggle, wiggle, wiggle\r\nWiggle, wiggle, wiggle\r\nWiggle, wiggle, wiggle\r\nJust a little bit\r\n\r\nPatty cake, patty cake with no hands\r\nGot me in this club, making wedding plans\r\nIf I take pictures while you do your dance\r\nI could make you famous on Instagram\r\n\r\nHot damn it, your booty like two planets\r\nGo ahead, and go ham sandwich\r\nWoah, I can't stand it\r\n\r\n'Cause you know what to do with that big fat butt\r\n\r\nWiggle, wiggle, wiggle\r\nWiggle, wiggle, wiggle\r\nWiggle, wiggle, wiggle\r\nJust a little bit\r\n\r\nCadillac Cadillac, pop that trunk\r\nLet's take a shot, Alley oop that dunk\r\nTired of working that nine to five\r\nOh, baby let me come and change your life\r\n\r\nHot damn it, your booty like two planets\r\nGo ahead, and go ham sandwich\r\nWoah, I can't stand it\r\n\r\n'Cause you know what to do with that big fat butt\r\n\r\nWiggle, wiggle, wiggle\r\nWiggle, wiggle, wiggle\r\nWiggle, wiggle, wiggle\r\nJust a little bit\r\n\r\nShake what your mamma gave you, misbehave you\r\nI just wanna strip you, dip you, flip you,\r\nBubble bathe you\r\nWhat they do\r\nTaste my raindrops, k boo?\r\nNow what you're willing, what you wanting, what you may do\r\nCompletely separated 'til I deeply penetrate it\r\nThen I take it out and wipe it off\r\nEat it, ate it, love it, hate it\r\nOverstated, underrated, everywhere I being King\r\nYou wiggle, wiggle for the D-O-double G again\r\n\r\nCome on baby, turn around\r\nYou're a star, girl, take a bow\r\nIt's just one thing that's killing me\r\nHow do you fit that in them jeans?\r\n\r\nYou know what to do with that big fat butt\r\n\r\nWiggle, wiggle, wiggle\r\nWiggle, wiggle, wiggle\r\nWiggle, wiggle, wiggle\r\nJust a little bit\r\n\r\nNow make it clap\r\nWiggle, wiggle, wiggle\r\nNow make it clap\r\nWiggle, wiggle, wiggle\r\nMake it clap\r\nNow make it clap\r\n\r\nDamn, baby, you got a bright future behind you", "music": "music/Snoop_Dogg_Jason_Derulo_-_Wiggle_48263756.mp3", "singer": [8, 5], "genre": [2, 3]}}, {"model": "music.music", "pk": 3, "fields": {"title": "Звезда по имени солнце", "group": 1, "public_date": "2017-11-27", "text_song": "Белый снег, серый лед, на растрескавшейся земле.\r\nОдеялом лоскутным на ней - город в дорожной петле.\r\nА над городом плывут облака, закрывая небесный свет.\r\nА над городом - желтый дым, городу две тысячи лет,\r\nПрожитых под светом Звезды по имени Солнце...\r\nИ две тысячи лет - война, война без особых причин.\r\nВойна - дело молодых, лекарство против морщин.\r\nКрасная, красная кровь - через час уже просто земля,\r\nЧерез два на ней цветы и трава, через три она снова жива\r\nИ согрета лучами Звезды по имени Солнце...\r\nИ мы знаем, что так было всегда, что Судьбою больше любим,\r\nКто живет по законам другим и кому умирать молодым.\r\nОн не помнит слово \"да\" и слово \"нет\", он не помнит ни чинов, ни имен.\r\nИ способен дотянуться до звезд, не считая, что это сон,\r\nИ упасть, опаленным Звездой по имени Солнце...", "music": "music/Kino_-_Zvezda_po_imeni_Solnce_47828842.mp3", "singer": [1], "genre": [1]}}, {"model": "news.photo", "pk": 3, "fields": {"image": "news/jordan-blake-a-skylit-drive-tim-mosenfelder-1.jpg", "title": "Default Title"}}, {"model": "news.photo", "pk": 4, "fields": {"image": "news/30565a377bdcabf2d621a8648d233a8056d2b913.webp", "title": "Default Title"}}, {"model": "news.photo", "pk": 5, "fields": {"image": "news/16df92a17638efc36fad28d24ef6b53208abcc56.webp", "title": "Новые российские альбомы: Big Baby Tape, Гио Пика и Кравц"}}, {"model": "news.photo", "pk": 6, "fields": {"image": "news/48e99e75057c36f6d0f4eae440afb9c0.jpeg", "title": "Default Title1"}}, {"model": "news.photo", "pk": 7, "fields": {"image": "news/48e99e75057c36f6d0f4eae440afb9c0_mAT5eTA.jpeg", "title": "Настасья"}}, {"model": "news.photo", "pk": 8, "fields": {"image": "news/48e99e75057c36f6d0f4eae440afb9c0_jBA3zb6.jpeg", "title": "настасья"}}, {"model": "news.photo", "pk": 9, "fields": {"image": "news/f872b24d2aa34cf2f12a15cdd9aad3239e0ac49a.webp", "title": "Инстасамка"}}, {"model": "news.news", "pk": 1, "fields": {"title": "Гуф пришел к вилле бывшей жены Юлии с кастетом", "public_date": "2023-11-29T19:16:12.688Z", "description": "Артист на английском языке попытался убедить охранника пустить его в дом. «Хочу знать, с кем моя дочь и моя жена. Юль, я буду ждать, пока не проснется ребенок, мне все равно», — заявил Гуф. Позже пост был удален.\r\n\r\nВ апреле стало известно, что исполнитель разводится с Королевой. Далее пара ненадолго воссоединялась, но в июле окончательно решила развестись. 20 октября они расторгли брак. Музыкант будет продолжать участвовать в воспитании общего с девушкой ребенка, Тины.\r\n\r\nВ прошлом месяце рэпер признался, что изменял Юлии в начале отношений.", "slug": "guf-prishel-k-ville-byvshej-zheny-yulii-s-kastetom", "photos": [6]}}, {"model": "news.news", "pk": 2, "fields": {"title": "Новые российские альбомы: Big Baby Tape, Гио Пика и Кравц", "public_date": "2023-11-29T20:00:20.093Z", "description": "Гио Пика, Кравц — 60 секунд до зимы\r\nГио Пика и Кравц продолжают свое сотрудничество, придерживаясь знакомой линии, — это уже второй их альбом за уходящий год. Его название иронично рифмуется с прошлогодней работой под названием «1000 лет до весны». Внутри все по-старому, хотя и звучит по-новому. Реальная жизнь, истории о которой завернуты в блестящую бумажку из любовной лирики.", "slug": "novye-rossijskie-albomy-big-baby-tape-gio-pika-i-kravc", "photos": [5]}}, {"model": "news.news", "pk": 3, "fields": {"title": "Настасья Самбурская раскрыла свою самую необычную роль", "public_date": "2023-11-30T05:59:39.807Z", "description": "Актриса Самбурская назвала роль ведьмы в вузе самой необычной в своей карьере. Звезда исполнила ее в 2008 году, когда училась в ГИТИСе. В финале постановки злую колдунью убили.\r\nДля роли Настасья использовала накладной нос и парик с всклокоченными седыми волосами.\r\n\r\n«В общем, я была старой ведьмой. Разговаривала таким голосом: \"Почтеннейший господин…\"», — рассказала артистка в беседе с Пятым каналом.\r\n\r\nВ этом году Самбурской предложили сняться в продолжении сериала «Универ», но она отказалась. Актрису не устроил гонорар.", "slug": "nastasya-samburskaya-raskryla-svoyu-samuyu-neobychnuyu-rol", "photos": [7]}}, {"model": "news.news", "pk": 4, "fields": {"title": "Инстасамка пожаловалась на слив фото с ее тайной свадьбы", "public_date": "2023-11-30T06:06:30.837Z", "description": "Рэп-исполнительница Дарья Зотеева, известная как Инстасамка, сообщила в личном блоге, что неизвестный опубликовал в сети фотографии с ее закрытой свадьбы с Олегом Еропкиным (он же Moneyken). Предположительно, торжество прошло в августе 2023 года.\r\n«Слили наши фотки со свадьбы, которую мы делали как частное мероприятие... Плачу. Хотела оставить это событие только для своих... Что за люди», — написала звезда.", "slug": "instasamka-pozhalovalas-na-sliv-foto-s-ee-tajnoj-svadby", "photos": [9]}}]